fairworkflows/__init__.py
fairworkflows/_version.py
fairworkflows/config.py
fairworkflows/fairstep.py
fairworkflows/fairworkflow.py
fairworkflows/linguistic_system.py
fairworkflows/manual_assistant.py
fairworkflows/namespaces.py
fairworkflows/prov.py
fairworkflows/rdf_wrapper.py
fairworkflows/resources/plex-shapes.ttl
fairworkflows-0.3.0.dist-info/LICENSE
fairworkflows-0.3.0.dist-info/METADATA
fairworkflows-0.3.0.dist-info/WHEEL
fairworkflows-0.3.0.dist-info/top_level.txt
fairworkflows-0.3.0.dist-info/RECORD
