Metadata-Version: 2.1
Name: fairworkflows
Version: 0.3.0
Summary: FAIRWorkflows python library
Home-page: https://github.com/fair-workflows/fairworkflows/
Author: Robin Richardson, Djura Smits, Sven van den Burg
Author-email: r.richardson@esciencecenter.nl
License: UNKNOWN
Platform: UNKNOWN
Classifier: Programming Language :: Python :: 3
Classifier: License :: OSI Approved :: Apache Software License
Classifier: Operating System :: OS Independent
Requires-Python: >=3.6
Requires-Dist: nanopub (==1.2.7)
Requires-Dist: networkx (~=2.5)
Requires-Dist: pytest
Requires-Dist: pyyaml
Requires-Dist: rdflib (<6.0.0,>=5.0.0)
Requires-Dist: requests
Requires-Dist: pyshacl (>=0.14.1)
Requires-Dist: noodles (==0.3.3)
Requires-Dist: Jinja2 (==2.11.3)
Provides-Extra: dev
Requires-Dist: coveralls ; extra == 'dev'
Requires-Dist: flaky ; extra == 'dev'
Requires-Dist: graphviz (==0.14.1) ; extra == 'dev'
Requires-Dist: pytest ; extra == 'dev'
Requires-Dist: pytest-cov ; extra == 'dev'
Requires-Dist: recommonmark ; extra == 'dev'
Requires-Dist: sphinx ; extra == 'dev'
Requires-Dist: sphinx-rtd-theme ; extra == 'dev'
